setup.py
api_auth/__init__.py
api_auth/admin.py
api_auth/exceptions.py
api_auth/models.py
api_auth/settings.py
api_auth/views.py
api_auth/migrations/0001_initial.py
api_auth/migrations/__init__.py
django_api_auth.egg-info/PKG-INFO
django_api_auth.egg-info/SOURCES.txt
django_api_auth.egg-info/dependency_links.txt
django_api_auth.egg-info/not-zip-safe
django_api_auth.egg-info/top_level.txt