Metadata-Version: 1.0
Name: django-api-auth
Version: 0.3
Summary: django-api-auth leverages tokens for authentication and was built for use with the Angular HTTP Auth Interceptor
Home-page: http://github.com/cridenour/django-api-auth
Author: Chris Ridenour
Author-email: chrisridenour@gmail.com
License: MIT
Platform: UNKNOWN
